README.rst
setup.py
keyvalueformatter/__init__.py
keyvalueformatter.egg-info/PKG-INFO
keyvalueformatter.egg-info/SOURCES.txt
keyvalueformatter.egg-info/dependency_links.txt
keyvalueformatter.egg-info/requires.txt
keyvalueformatter.egg-info/top_level.txt