Metadata-Version: 1.1
Name: keyvalueformatter
Version: 0.0.2
Summary: Allows easy key=value formatting for standard python logging
Home-page: https://github.com/KyleJamesWalker/keyvalueformatter
Author: Kyle James Walker
Author-email: KyleJamesWalker@gmail.com
License: MIT
Platform: UNKNOWN
Classifier: Development Status :: 2 - Pre-Alpha
Classifier: Intended Audience :: Developers
Classifier: License :: OSI Approved :: MIT License
Classifier: Natural Language :: English
Classifier: Programming Language :: Python :: 2.7
Classifier: Programming Language :: Python :: 3.5
